tabular_classification_package/__init__.py
tabular_classification_package/k_neighbors_classifier.py
tabular_classification_package/random_forest_classifier.py
tabular_classification_package/tabular_classification_model.py
tabular_classification_package/tabular_classification_task.py
tabular_classification_package-0.0.2.dist-info/METADATA
tabular_classification_package-0.0.2.dist-info/WHEEL
tabular_classification_package-0.0.2.dist-info/entry_points.txt
tabular_classification_package-0.0.2.dist-info/RECORD
