Metadata-Version: 2.1
Name: tabular_classification_package
Version: 0.0.2
Summary: Tabular Classification Package
Project-URL: Homepage, https://github.com/DashAISoftware/DashAI
Project-URL: Issues, https://github.com/DashAISoftware/DashAI/issues
Author-email: DashAI team <dashaisoftware@gmail.com>
Requires-Python: >=3.8
Requires-Dist: scikit-learn>=1.2.1
